[
    [
        {
            "word": "whet",
            "phonetic": "/\u02c8w\u025bt/",
            "phonetics": [
                {
                    "text": "/\u02c8w\u025bt/"
                },
                {
                    "text": "/\u02c8w\u025bt/"
                }
            ],
            "meanings": [
                {
                    "partOfSpeech": "noun",
                    "definitions": [
                        {
                            "definition": "The act of whetting something.",
                            "synonyms": [],
                            "antonyms": []
                        },
                        {
                            "definition": "That which whets or sharpens; especially, an appetizer.",
                            "synonyms": [],
                            "antonyms": []
                        }
                    ],
                    "synonyms": [],
                    "antonyms": []
                },
                {
                    "partOfSpeech": "verb",
                    "definitions": [
                        {
                            "definition": "To hone or rub on with some substance, as a piece of stone, for the purpose of sharpening \u2013 see whetstone.",
                            "synonyms": [],
                            "antonyms": []
                        },
                        {
                            "definition": "To stimulate or make more keen.",
                            "synonyms": [],
                            "antonyms": [],
                            "example": "to whet one's appetite or one's courage"
                        },
                        {
                            "definition": "To preen.",
                            "synonyms": [],
                            "antonyms": []
                        }
                    ],
                    "synonyms": [],
                    "antonyms": []
                }
            ]
        }
    ],
    [
        {
            "word": "propinquity",
            "phonetic": "/p\u0279\u0259\u02c8p\u026a\u014b.kw\u026a.ti/",
            "phonetics": [
                {
                    "text": "/p\u0279\u0259\u02c8p\u026a\u014b.kw\u026a.ti/"
                }
            ],
            "meanings": [
                {
                    "partOfSpeech": "noun",
                    "definitions": [
                        {
                            "definition": "Nearness or proximity.",
                            "synonyms": [],
                            "antonyms": []
                        },
                        {
                            "definition": "Affiliation or similarity.",
                            "synonyms": [],
                            "antonyms": []
                        }
                    ],
                    "synonyms": [
                        "appropinquity"
                    ],
                    "antonyms": []
                }
            ]
        }
    ],
    [
        {
            "word": "pertinent",
            "phonetic": "/\u02c8p\u0259\u02d0t\u026an\u0259nt/",
            "phonetics": [
                {
                    "text": "/\u02c8p\u0259\u02d0t\u026an\u0259nt/"
                },
                {}
            ],
            "meanings": [
                {
                    "partOfSpeech": "adjective",
                    "definitions": [
                        {
                            "definition": "Important with regard to (a subject or matter); relevant",
                            "synonyms": [],
                            "antonyms": []
                        }
                    ],
                    "synonyms": [],
                    "antonyms": []
                }
            ]
        }
    ]
]