[
    [
        {
            "word": "feral",
            "phonetic": "/\u02c8f\u025b\u0279\u0259l/",
            "phonetics": [
                {
                    "text": "/\u02c8f\u025b\u0279\u0259l/"
                }
            ],
            "meanings": [
                {
                    "partOfSpeech": "noun",
                    "definitions": [
                        {
                            "definition": "A domesticated animal that has returned to the wild; an animal, particularly a domesticated animal, living independently of humans.",
                            "synonyms": [],
                            "antonyms": []
                        },
                        {
                            "definition": "A contemptible young person, a lout, a person who behaves wildly.",
                            "synonyms": [],
                            "antonyms": []
                        },
                        {
                            "definition": "A person who has isolated themselves from the outside world; one living an alternative lifestyle.",
                            "synonyms": [],
                            "antonyms": []
                        },
                        {
                            "definition": "(furry subculture) A character in furry art or literature which has the physical characteristics (body) of a regular animal (typically quadripedal), that may or may not be able to communicate with humans or anthros (contrasts anthro)",
                            "synonyms": [],
                            "antonyms": [],
                            "example": "The story is about a group of ferals which have to explore the ruins of society after the humans die out."
                        }
                    ],
                    "synonyms": [],
                    "antonyms": []
                },
                {
                    "partOfSpeech": "adjective",
                    "definitions": [
                        {
                            "definition": "Wild, untamed, especially of domesticated animals having returned to the wild.",
                            "synonyms": [],
                            "antonyms": []
                        },
                        {
                            "definition": "(of a person) Contemptible, unruly, misbehaved.",
                            "synonyms": [],
                            "antonyms": []
                        }
                    ],
                    "synonyms": [],
                    "antonyms": []
                }
            ]
        }
    ],
    [
        {
            "word": "nugatory",
            "phonetic": "/\u02c8nju\u02d0\u0261\u0259t\u0254\u0279i/",
            "phonetics": [
                {
                    "text": "/\u02c8nju\u02d0\u0261\u0259t\u0254\u0279i/"
                }
            ],
            "meanings": [
                {
                    "partOfSpeech": "adjective",
                    "definitions": [
                        {
                            "definition": "Trivial, trifling or of little importance.",
                            "synonyms": [],
                            "antonyms": []
                        },
                        {
                            "definition": "Ineffective, invalid or futile.",
                            "synonyms": [],
                            "antonyms": []
                        },
                        {
                            "definition": "Having no force, inoperative, ineffectual.",
                            "synonyms": [],
                            "antonyms": []
                        },
                        {
                            "definition": "Removable from a computer program with safety, but harmless if retained.",
                            "synonyms": [],
                            "antonyms": []
                        }
                    ],
                    "synonyms": [],
                    "antonyms": []
                }
            ]
        }
    ],
    [
        {
            "word": "tawdry",
            "phonetic": "/\u02c8t\u0254\u02d0d\u0279i/",
            "phonetics": [
                {
                    "text": "/\u02c8t\u0254\u02d0d\u0279i/"
                }
            ],
            "meanings": [
                {
                    "partOfSpeech": "noun",
                    "definitions": [
                        {
                            "definition": "Tawdry lace.",
                            "synonyms": [],
                            "antonyms": []
                        },
                        {
                            "definition": "Anything gaudy and cheap; pretentious finery.",
                            "synonyms": [],
                            "antonyms": []
                        }
                    ],
                    "synonyms": [],
                    "antonyms": []
                },
                {
                    "partOfSpeech": "adjective",
                    "definitions": [
                        {
                            "definition": "(of clothing, appearance, etc.) Cheap and gaudy; showy.",
                            "synonyms": [],
                            "antonyms": []
                        },
                        {
                            "definition": "(of character, behavior, situations, etc.) Unseemly, base, shameful.",
                            "synonyms": [],
                            "antonyms": []
                        }
                    ],
                    "synonyms": [
                        "sordid"
                    ],
                    "antonyms": []
                }
            ]
        }
    ]
]