[
    [
        {
            "word": "jocular",
            "phonetics": [
                {},
                {
                    "text": "/\u02c8d\u0292\u0252kj\u028al\u0259/"
                },
                {
                    "text": "/\u02c8d\u0292\u0251kj\u0259l\u025a/"
                }
            ],
            "meanings": [
                {
                    "partOfSpeech": "adjective",
                    "definitions": [
                        {
                            "definition": "Humorous, amusing or joking.",
                            "synonyms": [],
                            "antonyms": [],
                            "example": "All we had was a short and jocular conversation."
                        }
                    ],
                    "synonyms": [
                        "joculous",
                        "jokey",
                        "silly"
                    ],
                    "antonyms": [
                        "heartfelt",
                        "serious",
                        "sincere"
                    ]
                }
            ]
        }
    ],
    [
        {
            "word": "nefarious",
            "phonetic": "/n\u025b\u02c8f\u025b\u0259\u0279i.\u0259s/",
            "phonetics": [
                {
                    "text": "/n\u025b\u02c8f\u025b\u0259\u0279i.\u0259s/"
                },
                {
                    "text": "/n\u026a\u02c8f\u025b\u02d0\u0279\u026a.\u0259s/"
                }
            ],
            "meanings": [
                {
                    "partOfSpeech": "adjective",
                    "definitions": [
                        {
                            "definition": "Sinful, villainous, criminal, or wicked, especially when noteworthy or notorious for such characteristics.",
                            "synonyms": [
                                "evil",
                                "good-for-nothing",
                                "iniquitous",
                                "sinister",
                                "underhanded",
                                "vile"
                            ],
                            "antonyms": [],
                            "example": "Aliens have a nefarious connotation in many science fiction books."
                        }
                    ],
                    "synonyms": [
                        "evil",
                        "good-for-nothing",
                        "iniquitous",
                        "sinister",
                        "underhanded",
                        "vile"
                    ],
                    "antonyms": []
                }
            ]
        }
    ],
    [
        {
            "word": "writhe",
            "phonetic": "/\u0279a\u026a\u00f0/",
            "phonetics": [
                {
                    "text": "/\u0279a\u026a\u00f0/"
                }
            ],
            "meanings": [
                {
                    "partOfSpeech": "noun",
                    "definitions": [
                        {
                            "definition": "A contortion.",
                            "synonyms": [],
                            "antonyms": []
                        },
                        {
                            "definition": "(knot theory) The number of negative crossings subtracted from the number of positive crossings in a knot",
                            "synonyms": [],
                            "antonyms": []
                        }
                    ],
                    "synonyms": [],
                    "antonyms": []
                },
                {
                    "partOfSpeech": "verb",
                    "definitions": [
                        {
                            "definition": "To twist, to wring (something).",
                            "synonyms": [],
                            "antonyms": []
                        },
                        {
                            "definition": "To contort (a part of the body).",
                            "synonyms": [],
                            "antonyms": []
                        },
                        {
                            "definition": "To twist or contort the body; to be distorted.",
                            "synonyms": [],
                            "antonyms": []
                        },
                        {
                            "definition": "To extort.",
                            "synonyms": [],
                            "antonyms": []
                        }
                    ],
                    "synonyms": [],
                    "antonyms": []
                }
            ]
        }
    ]
]