[
    [
        {
            "word": "confluence",
            "phonetic": "/\u02c8k\u0252nflu\u0259ns/",
            "phonetics": [
                {
                    "text": "/\u02c8k\u0252nflu\u0259ns/"
                }
            ],
            "meanings": [
                {
                    "partOfSpeech": "noun",
                    "definitions": [
                        {
                            "definition": "The place where two rivers, streams, or other continuously flowing bodies of water meet and become one, especially where a tributary joins a river.",
                            "synonyms": [],
                            "antonyms": [],
                            "example": "We encountered an abandoned boat at the confluence of the Mississippi and Ohio Rivers."
                        },
                        {
                            "definition": "The act of combining which occurs at the place where rivers and the lake meet.",
                            "synonyms": [],
                            "antonyms": [],
                            "example": "The confluence of the rivers produced a great rush of water."
                        },
                        {
                            "definition": "A convergence or combination of forces, people, or things.",
                            "synonyms": [],
                            "antonyms": [],
                            "example": "The confluence of our skills resulted in a successful home renovation project."
                        },
                        {
                            "definition": "The proportion of cells, in a culture medium, that adhere to each other",
                            "synonyms": [],
                            "antonyms": []
                        },
                        {
                            "definition": "In rewriting systems, property describing which terms can be rewritten with other, equivalent terms.",
                            "synonyms": [],
                            "antonyms": []
                        }
                    ],
                    "synonyms": [
                        "conflux"
                    ],
                    "antonyms": []
                }
            ]
        }
    ],
    [
        {
            "word": "sibilant",
            "phonetics": [
                {},
                {
                    "text": "/\u02c8s\u026ab.\u026a.l\u0259nt/"
                },
                {
                    "text": "/\u02c8s\u026ab.\u026a.l\u0259nt/"
                }
            ],
            "meanings": [
                {
                    "partOfSpeech": "noun",
                    "definitions": [
                        {
                            "definition": "A consonant having a hissing sound such as the 's' or 'sh' in 'sash' or 'surge'.",
                            "synonyms": [
                                "groove fricative"
                            ],
                            "antonyms": []
                        }
                    ],
                    "synonyms": [
                        "groove fricative"
                    ],
                    "antonyms": []
                },
                {
                    "partOfSpeech": "adjective",
                    "definitions": [
                        {
                            "definition": "Characterized by a hissing sound such as the \"s\" or \"sh\" in sash or surge.",
                            "synonyms": [],
                            "antonyms": []
                        }
                    ],
                    "synonyms": [],
                    "antonyms": []
                }
            ]
        }
    ],
    [
        {
            "word": "ken",
            "phonetic": "/k\u025bn/",
            "phonetics": [
                {
                    "text": "/k\u025bn/"
                }
            ],
            "meanings": [
                {
                    "partOfSpeech": "verb",
                    "definitions": [
                        {
                            "definition": "To give birth, conceive, beget, be born; to develop (as a fetus); to nourish, sustain (as life).",
                            "synonyms": [],
                            "antonyms": []
                        }
                    ],
                    "synonyms": [],
                    "antonyms": []
                }
            ]
        },
        {
            "word": "ken",
            "phonetic": "/k\u025bn/",
            "phonetics": [
                {
                    "text": "/k\u025bn/"
                }
            ],
            "meanings": [
                {
                    "partOfSpeech": "noun",
                    "definitions": [
                        {
                            "definition": "Knowledge, perception, or sight.",
                            "synonyms": [],
                            "antonyms": []
                        },
                        {
                            "definition": "Range of sight.",
                            "synonyms": [],
                            "antonyms": []
                        }
                    ],
                    "synonyms": [],
                    "antonyms": []
                },
                {
                    "partOfSpeech": "verb",
                    "definitions": [
                        {
                            "definition": "To know, perceive or understand.",
                            "synonyms": [],
                            "antonyms": []
                        },
                        {
                            "definition": "To discover by sight; to catch sight of; to descry.",
                            "synonyms": [],
                            "antonyms": []
                        }
                    ],
                    "synonyms": [],
                    "antonyms": []
                }
            ]
        },
        {
            "word": "ken",
            "phonetic": "/k\u025bn/",
            "phonetics": [
                {
                    "text": "/k\u025bn/"
                }
            ],
            "meanings": [
                {
                    "partOfSpeech": "noun",
                    "definitions": [
                        {
                            "definition": "(thieves' cant) A house, especially a den of thieves.",
                            "synonyms": [],
                            "antonyms": []
                        }
                    ],
                    "synonyms": [],
                    "antonyms": []
                }
            ]
        },
        {
            "word": "ken",
            "phonetic": "/k\u025bn/",
            "phonetics": [
                {
                    "text": "/k\u025bn/"
                }
            ],
            "meanings": [
                {
                    "partOfSpeech": "noun",
                    "definitions": [
                        {
                            "definition": "A Japanese unit of length equal to six shakus",
                            "synonyms": [],
                            "antonyms": []
                        }
                    ],
                    "synonyms": [],
                    "antonyms": []
                }
            ]
        }
    ]
]